sqlalchemy_greenplum/__init__.py
sqlalchemy_greenplum/alembic_gp.py
sqlalchemy_greenplum/dialect.py
sqlalchemy_greenplum/provision.py
sqlalchemy_greenplum/requirements.py
test/__init__.py
test/conftest.py
test/test_suite.py
sqlalchemy_greenplum-0.2.1.dist-info/LICENSE
sqlalchemy_greenplum-0.2.1.dist-info/METADATA
sqlalchemy_greenplum-0.2.1.dist-info/WHEEL
sqlalchemy_greenplum-0.2.1.dist-info/entry_points.txt
sqlalchemy_greenplum-0.2.1.dist-info/top_level.txt
sqlalchemy_greenplum-0.2.1.dist-info/RECORD
