Metadata-Version: 2.1
Name: sqlalchemy-greenplum
Version: 0.2.1
Summary: SQLAlchemy dialect for Greenplum Database
Home-page: https://github.com/PlaidCloud/sqlalchemy-greenplum
Author: Patrick Buxton
Author-email: patrick.buxton@tartansolutions.com
License: Apache License 2.0
Classifier: Development Status :: 3 - Alpha
Classifier: Intended Audience :: Developers
Classifier: License :: Other/Proprietary License
Classifier: Operating System :: OS Independent
Classifier: Programming Language :: Python
Classifier: Programming Language :: Python :: 3
Classifier: Programming Language :: Python :: 3.8
Classifier: Programming Language :: Python :: 3.9
Classifier: Programming Language :: Python :: 3.10
Classifier: Programming Language :: Python :: 3.11
Classifier: Programming Language :: Python :: 3.12
Classifier: Programming Language :: SQL
Classifier: Topic :: Database
Classifier: Topic :: Database :: Front-Ends
Classifier: Topic :: Software Development
Classifier: Topic :: Software Development :: Libraries :: Python Modules
License-File: LICENSE
Requires-Dist: sqlalchemy <3,>=1.4.0
Requires-Dist: psycopg2-binary
